{
  "AAPL": {
    "history": [
      {
        "time": "2025-05-20 02:36:24",
        "price": 622.49,
        "volume": 1363
      },
      {
        "time": "2025-05-20 02:36:34",
        "price": 699.14,
        "volume": 1276
      },
      {
        "time": "2025-05-20 02:36:44",
        "price": 793.31,
        "volume": 1214
      },
      {
        "time": "2025-05-20 02:38:17",
        "price": 824.67,
        "volume": 1233
      },
      {
        "time": "2025-05-20 02:38:27",
        "price": 766.26,
        "volume": 1243
      },
      {
        "time": "2025-05-20 02:38:37",
        "price": 813.31,
        "volume": 1200
      },
      {
        "time": "2025-05-20 02:38:47",
        "price": 906.27,
        "volume": 1226
      },
      {
        "time": "2025-05-20 02:38:57",
        "price": 980.21,
        "volume": 1277
      },
      {
        "time": "2025-05-20 02:39:07",
        "price": 887.48,
        "volume": 1301
      },
      {
        "time": "2025-05-20 02:39:17",
        "price": 946.85,
        "volume": 1400
      },
      {
        "time": "2025-05-20 02:39:27",
        "price": 950.24,
        "volume": 1445
      },
      {
        "time": "2025-05-20 02:39:37",
        "price": 1027.88,
        "volume": 1415
      },
      {
        "time": "2025-05-20 02:39:47",
        "price": 1092.39,
        "volume": 1365
      },
      {
        "time": "2025-05-20 02:39:57",
        "price": 1023.4,
        "volume": 1440
      },
      {
        "time": "2025-05-20 02:40:07",
        "price": 984.39,
        "volume": 1415
      },
      {
        "time": "2025-05-20 02:40:17",
        "price": 928.22,
        "volume": 1412
      },
      {
        "time": "2025-05-20 02:40:27",
        "price": 855.72,
        "volume": 1424
      },
      {
        "time": "2025-05-20 02:40:37",
        "price": 910.01,
        "volume": 1465
      },
      {
        "time": "2025-05-20 02:40:47",
        "price": 943.37,
        "volume": 1433
      },
      {
        "time": "2025-05-20 02:40:57",
        "price": 912.28,
        "volume": 1400
      },
      {
        "time": "2025-05-20 02:41:07",
        "price": 964.88,
        "volume": 1416
      },
      {
        "time": "2025-05-20 02:48:22",
        "price": 989.61,
        "volume": 1372
      },
      {
        "time": "2025-05-20 02:48:32",
        "price": 908.06,
        "volume": 1413
      },
      {
        "time": "2025-05-20 02:48:42",
        "price": 895.1,
        "volume": 1347
      },
      {
        "time": "2025-05-20 02:48:52",
        "price": 886.27,
        "volume": 1358
      },
      {
        "time": "2025-05-20 02:49:02",
        "price": 857.81,
        "volume": 1426
      },
      {
        "time": "2025-05-20 02:49:12",
        "price": 892.17,
        "volume": 1514
      },
      {
        "time": "2025-05-20 02:49:22",
        "price": 870.2,
        "volume": 1574
      },
      {
        "time": "2025-05-20 02:56:35",
        "price": 816.61,
        "volume": 1479
      },
      {
        "time": "2025-05-20 02:56:45",
        "price": 838.95,
        "volume": 1415
      },
      {
        "time": "2025-05-20 02:56:55",
        "price": 833.6,
        "volume": 1433
      },
      {
        "time": "2025-05-20 02:57:05",
        "price": 812.69,
        "volume": 1406
      },
      {
        "time": "2025-05-20 02:57:15",
        "price": 826.36,
        "volume": 1314
      },
      {
        "time": "2025-05-20 02:57:25",
        "price": 808.93,
        "volume": 1284
      },
      {
        "time": "2025-05-20 02:57:35",
        "price": 725.28,
        "volume": 1370
      },
      {
        "time": "2025-05-20 02:57:45",
        "price": 808.98,
        "volume": 1446
      },
      {
        "time": "2025-05-20 02:57:55",
        "price": 841.5,
        "volume": 1398
      },
      {
        "time": "2025-05-20 02:58:05",
        "price": 859.19,
        "volume": 1422
      },
      {
        "time": "2025-05-20 02:58:15",
        "price": 915.74,
        "volume": 1342
      },
      {
        "time": "2025-05-20 02:58:25",
        "price": 895.05,
        "volume": 1355
      },
      {
        "time": "2025-05-20 02:58:35",
        "price": 853.85,
        "volume": 1382
      },
      {
        "time": "2025-05-20 02:58:45",
        "price": 835.99,
        "volume": 1347
      },
      {
        "time": "2025-05-20 02:58:55",
        "price": 757.96,
        "volume": 1375
      },
      {
        "time": "2025-05-20 02:59:05",
        "price": 671.97,
        "volume": 1424
      },
      {
        "time": "2025-05-20 03:28:54",
        "price": 658.76,
        "volume": 1346
      },
      {
        "time": "2025-05-20 03:29:04",
        "price": 654.48,
        "volume": 1430
      },
      {
        "time": "2025-05-20 03:29:14",
        "price": 671.5,
        "volume": 1459
      },
      {
        "time": "2025-05-20 03:29:24",
        "price": 770.43,
        "volume": 1466
      },
      {
        "time": "2025-05-20 03:29:34",
        "price": 772.02,
        "volume": 1420
      },
      {
        "time": "2025-05-20 03:29:44",
        "price": 741.61,
        "volume": 1387
      },
      {
        "time": "2025-05-20 03:29:54",
        "price": 746.47,
        "volume": 1381
      },
      {
        "time": "2025-05-20 03:30:04",
        "price": 701.72,
        "volume": 1409
      },
      {
        "time": "2025-05-20 03:30:14",
        "price": 730.96,
        "volume": 1339
      },
      {
        "time": "2025-05-20 03:30:24",
        "price": 744.46,
        "volume": 1354
      },
      {
        "time": "2025-05-20 03:30:34",
        "price": 656.53,
        "volume": 1351
      },
      {
        "time": "2025-05-20 03:30:44",
        "price": 672.16,
        "volume": 1361
      },
      {
        "time": "2025-05-20 03:30:54",
        "price": 647.76,
        "volume": 1428
      },
      {
        "time": "2025-05-20 03:31:04",
        "price": 723.38,
        "volume": 1385
      },
      {
        "time": "2025-05-20 03:51:17",
        "price": 664.17,
        "volume": 1322
      },
      {
        "time": "2025-05-20 03:51:27",
        "price": 608.54,
        "volume": 1420
      },
      {
        "time": "2025-05-20 03:51:37",
        "price": 532.17,
        "volume": 1486
      },
      {
        "time": "2025-05-20 03:51:47",
        "price": 618.28,
        "volume": 1570
      },
      {
        "time": "2025-05-20 03:51:49",
        "price": 560.55,
        "volume": 1637
      },
      {
        "time": "2025-05-20 03:51:59",
        "price": 646.29,
        "volume": 1655
      },
      {
        "time": "2025-05-20 03:52:09",
        "price": 636.9,
        "volume": 1640
      },
      {
        "time": "2025-05-20 03:52:19",
        "price": 567.31,
        "volume": 1700
      },
      {
        "time": "2025-05-20 03:52:29",
        "price": 569.25,
        "volume": 1671
      },
      {
        "time": "2025-05-20 03:52:39",
        "price": 517.5,
        "volume": 1748
      },
      {
        "time": "2025-05-20 03:52:49",
        "price": 546.03,
        "volume": 1746
      },
      {
        "time": "2025-05-20 03:52:59",
        "price": 560.75,
        "volume": 1745
      }
    ]
  },
  "GOOGL": {
    "history": [
      {
        "time": "2025-05-20 02:36:24",
        "price": 33.74,
        "volume": 1838
      },
      {
        "time": "2025-05-20 02:36:34",
        "price": 23.44,
        "volume": 1830
      },
      {
        "time": "2025-05-20 02:36:44",
        "price": 14.56,
        "volume": 1807
      },
      {
        "time": "2025-05-20 02:38:17",
        "price": 1,
        "volume": 1808
      },
      {
        "time": "2025-05-20 02:38:27",
        "price": 1,
        "volume": 1850
      },
      {
        "time": "2025-05-20 02:38:37",
        "price": 28.51,
        "volume": 1836
      },
      {
        "time": "2025-05-20 02:38:47",
        "price": 8.93,
        "volume": 1742
      },
      {
        "time": "2025-05-20 02:38:57",
        "price": 1,
        "volume": 1731
      },
      {
        "time": "2025-05-20 02:39:07",
        "price": 38.9,
        "volume": 1704
      },
      {
        "time": "2025-05-20 02:39:17",
        "price": 1,
        "volume": 1802
      },
      {
        "time": "2025-05-20 02:39:27",
        "price": 1,
        "volume": 1854
      },
      {
        "time": "2025-05-20 02:39:37",
        "price": 1,
        "volume": 1827
      },
      {
        "time": "2025-05-20 02:39:47",
        "price": 9.78,
        "volume": 1735
      },
      {
        "time": "2025-05-20 02:39:57",
        "price": 49.25,
        "volume": 1708
      },
      {
        "time": "2025-05-20 02:40:07",
        "price": 17.54,
        "volume": 1748
      },
      {
        "time": "2025-05-20 02:40:17",
        "price": 20.32,
        "volume": 1679
      },
      {
        "time": "2025-05-20 02:40:27",
        "price": 1,
        "volume": 1643
      },
      {
        "time": "2025-05-20 02:40:37",
        "price": 1,
        "volume": 1572
      },
      {
        "time": "2025-05-20 02:40:47",
        "price": 1,
        "volume": 1518
      },
      {
        "time": "2025-05-20 02:40:57",
        "price": 59.72,
        "volume": 1443
      },
      {
        "time": "2025-05-20 02:41:07",
        "price": 1,
        "volume": 1443
      },
      {
        "time": "2025-05-20 02:48:22",
        "price": 2.7,
        "volume": 1357
      },
      {
        "time": "2025-05-20 02:48:32",
        "price": 52.78,
        "volume": 1354
      },
      {
        "time": "2025-05-20 02:48:42",
        "price": 33.39,
        "volume": 1360
      },
      {
        "time": "2025-05-20 02:48:52",
        "price": 14.44,
        "volume": 1322
      },
      {
        "time": "2025-05-20 02:49:02",
        "price": 1,
        "volume": 1264
      },
      {
        "time": "2025-05-20 02:49:12",
        "price": 18.17,
        "volume": 1294
      },
      {
        "time": "2025-05-20 02:49:22",
        "price": 92.61,
        "volume": 1303
      },
      {
        "time": "2025-05-20 02:56:35",
        "price": 21.26,
        "volume": 1368
      },
      {
        "time": "2025-05-20 02:56:45",
        "price": 1,
        "volume": 1290
      },
      {
        "time": "2025-05-20 02:56:55",
        "price": 1,
        "volume": 1309
      },
      {
        "time": "2025-05-20 02:57:05",
        "price": 21.97,
        "volume": 1337
      },
      {
        "time": "2025-05-20 02:57:15",
        "price": 1,
        "volume": 1239
      },
      {
        "time": "2025-05-20 02:57:25",
        "price": 1,
        "volume": 1224
      },
      {
        "time": "2025-05-20 02:57:35",
        "price": 1,
        "volume": 1258
      },
      {
        "time": "2025-05-20 02:57:45",
        "price": 1,
        "volume": 1178
      },
      {
        "time": "2025-05-20 02:57:55",
        "price": 4.02,
        "volume": 1140
      },
      {
        "time": "2025-05-20 02:58:05",
        "price": 1,
        "volume": 1136
      },
      {
        "time": "2025-05-20 02:58:15",
        "price": 28.74,
        "volume": 1092
      },
      {
        "time": "2025-05-20 02:58:25",
        "price": 92.49,
        "volume": 1156
      },
      {
        "time": "2025-05-20 02:58:35",
        "price": 85.49,
        "volume": 1085
      },
      {
        "time": "2025-05-20 02:58:45",
        "price": 10.91,
        "volume": 1056
      },
      {
        "time": "2025-05-20 02:58:55",
        "price": 1,
        "volume": 1129
      },
      {
        "time": "2025-05-20 02:59:05",
        "price": 57.11,
        "volume": 1199
      },
      {
        "time": "2025-05-20 03:28:54",
        "price": 5.47,
        "volume": 1124
      },
      {
        "time": "2025-05-20 03:29:04",
        "price": 23.53,
        "volume": 1173
      },
      {
        "time": "2025-05-20 03:29:14",
        "price": 1,
        "volume": 1133
      },
      {
        "time": "2025-05-20 03:29:24",
        "price": 1,
        "volume": 1177
      },
      {
        "time": "2025-05-20 03:29:34",
        "price": 1,
        "volume": 1256
      },
      {
        "time": "2025-05-20 03:29:44",
        "price": 1,
        "volume": 1169
      },
      {
        "time": "2025-05-20 03:29:54",
        "price": 1,
        "volume": 1202
      },
      {
        "time": "2025-05-20 03:30:04",
        "price": 87.13,
        "volume": 1149
      },
      {
        "time": "2025-05-20 03:30:14",
        "price": 100.92,
        "volume": 1067
      },
      {
        "time": "2025-05-20 03:30:24",
        "price": 8.3,
        "volume": 1137
      },
      {
        "time": "2025-05-20 03:30:34",
        "price": 94.62,
        "volume": 1095
      },
      {
        "time": "2025-05-20 03:30:44",
        "price": 134.37,
        "volume": 1052
      },
      {
        "time": "2025-05-20 03:30:54",
        "price": 193.94,
        "volume": 1065
      },
      {
        "time": "2025-05-20 03:31:04",
        "price": 186.26,
        "volume": 978
      },
      {
        "time": "2025-05-20 03:51:17",
        "price": 215.66,
        "volume": 997
      },
      {
        "time": "2025-05-20 03:51:27",
        "price": 180.61,
        "volume": 1058
      },
      {
        "time": "2025-05-20 03:51:37",
        "price": 247.86,
        "volume": 1001
      },
      {
        "time": "2025-05-20 03:51:47",
        "price": 331.1,
        "volume": 1024
      },
      {
        "time": "2025-05-20 03:51:49",
        "price": 257.03,
        "volume": 985
      },
      {
        "time": "2025-05-20 03:51:59",
        "price": 179.62,
        "volume": 914
      },
      {
        "time": "2025-05-20 03:52:09",
        "price": 193.88,
        "volume": 932
      },
      {
        "time": "2025-05-20 03:52:19",
        "price": 186.9,
        "volume": 832
      },
      {
        "time": "2025-05-20 03:52:29",
        "price": 186.72,
        "volume": 923
      },
      {
        "time": "2025-05-20 03:52:39",
        "price": 155.17,
        "volume": 872
      },
      {
        "time": "2025-05-20 03:52:49",
        "price": 88.96,
        "volume": 940
      },
      {
        "time": "2025-05-20 03:52:59",
        "price": 173.87,
        "volume": 964
      }
    ]
  },
  "TSLA": {
    "history": [
      {
        "time": "2025-05-20 02:36:24",
        "price": 609.79,
        "volume": 1191
      },
      {
        "time": "2025-05-20 02:36:34",
        "price": 656.52,
        "volume": 1277
      },
      {
        "time": "2025-05-20 02:36:44",
        "price": 702.53,
        "volume": 1354
      },
      {
        "time": "2025-05-20 02:38:17",
        "price": 755.22,
        "volume": 1412
      },
      {
        "time": "2025-05-20 02:38:27",
        "price": 702.99,
        "volume": 1497
      },
      {
        "time": "2025-05-20 02:38:37",
        "price": 618.9,
        "volume": 1488
      },
      {
        "time": "2025-05-20 02:38:47",
        "price": 685.47,
        "volume": 1497
      },
      {
        "time": "2025-05-20 02:38:57",
        "price": 652.22,
        "volume": 1569
      },
      {
        "time": "2025-05-20 02:39:07",
        "price": 738.3,
        "volume": 1527
      },
      {
        "time": "2025-05-20 02:39:17",
        "price": 645.81,
        "volume": 1444
      },
      {
        "time": "2025-05-20 02:39:27",
        "price": 646.58,
        "volume": 1381
      },
      {
        "time": "2025-05-20 02:39:37",
        "price": 692.35,
        "volume": 1345
      },
      {
        "time": "2025-05-20 02:39:47",
        "price": 686.71,
        "volume": 1355
      },
      {
        "time": "2025-05-20 02:39:57",
        "price": 753.96,
        "volume": 1290
      },
      {
        "time": "2025-05-20 02:40:07",
        "price": 756.51,
        "volume": 1269
      },
      {
        "time": "2025-05-20 02:40:17",
        "price": 851.68,
        "volume": 1239
      },
      {
        "time": "2025-05-20 02:40:27",
        "price": 766.49,
        "volume": 1182
      },
      {
        "time": "2025-05-20 02:40:37",
        "price": 799.96,
        "volume": 1094
      },
      {
        "time": "2025-05-20 02:40:47",
        "price": 782.51,
        "volume": 1084
      },
      {
        "time": "2025-05-20 02:40:57",
        "price": 755.32,
        "volume": 1096
      },
      {
        "time": "2025-05-20 02:41:07",
        "price": 684.28,
        "volume": 1158
      },
      {
        "time": "2025-05-20 02:48:22",
        "price": 769.5,
        "volume": 1206
      },
      {
        "time": "2025-05-20 02:48:32",
        "price": 743.62,
        "volume": 1261
      },
      {
        "time": "2025-05-20 02:48:42",
        "price": 808.6,
        "volume": 1201
      },
      {
        "time": "2025-05-20 02:48:52",
        "price": 774.58,
        "volume": 1186
      },
      {
        "time": "2025-05-20 02:49:02",
        "price": 803.27,
        "volume": 1218
      },
      {
        "time": "2025-05-20 02:49:12",
        "price": 840.96,
        "volume": 1171
      },
      {
        "time": "2025-05-20 02:49:22",
        "price": 893.79,
        "volume": 1271
      },
      {
        "time": "2025-05-20 02:56:35",
        "price": 934.83,
        "volume": 1329
      },
      {
        "time": "2025-05-20 02:56:45",
        "price": 865.52,
        "volume": 1393
      },
      {
        "time": "2025-05-20 02:56:55",
        "price": 880.64,
        "volume": 1295
      },
      {
        "time": "2025-05-20 02:57:05",
        "price": 838.29,
        "volume": 1258
      },
      {
        "time": "2025-05-20 02:57:15",
        "price": 796.35,
        "volume": 1340
      },
      {
        "time": "2025-05-20 02:57:25",
        "price": 888.66,
        "volume": 1321
      },
      {
        "time": "2025-05-20 02:57:35",
        "price": 922.65,
        "volume": 1380
      },
      {
        "time": "2025-05-20 02:57:45",
        "price": 962.27,
        "volume": 1378
      },
      {
        "time": "2025-05-20 02:57:55",
        "price": 870.57,
        "volume": 1405
      },
      {
        "time": "2025-05-20 02:58:05",
        "price": 800.49,
        "volume": 1383
      },
      {
        "time": "2025-05-20 02:58:15",
        "price": 880.91,
        "volume": 1339
      },
      {
        "time": "2025-05-20 02:58:25",
        "price": 949.99,
        "volume": 1428
      },
      {
        "time": "2025-05-20 02:58:35",
        "price": 891.12,
        "volume": 1332
      },
      {
        "time": "2025-05-20 02:58:45",
        "price": 986.43,
        "volume": 1384
      },
      {
        "time": "2025-05-20 02:58:55",
        "price": 979.62,
        "volume": 1360
      },
      {
        "time": "2025-05-20 02:59:05",
        "price": 905.2,
        "volume": 1333
      },
      {
        "time": "2025-05-20 03:28:54",
        "price": 993.32,
        "volume": 1353
      },
      {
        "time": "2025-05-20 03:29:04",
        "price": 1056.36,
        "volume": 1290
      },
      {
        "time": "2025-05-20 03:29:14",
        "price": 1051.64,
        "volume": 1330
      },
      {
        "time": "2025-05-20 03:29:24",
        "price": 1049.92,
        "volume": 1281
      },
      {
        "time": "2025-05-20 03:29:34",
        "price": 1104.49,
        "volume": 1319
      },
      {
        "time": "2025-05-20 03:29:44",
        "price": 1145.37,
        "volume": 1309
      },
      {
        "time": "2025-05-20 03:29:54",
        "price": 1158.03,
        "volume": 1212
      },
      {
        "time": "2025-05-20 03:30:04",
        "price": 1133.71,
        "volume": 1232
      },
      {
        "time": "2025-05-20 03:30:14",
        "price": 1039.95,
        "volume": 1325
      },
      {
        "time": "2025-05-20 03:30:24",
        "price": 1026.1,
        "volume": 1348
      },
      {
        "time": "2025-05-20 03:30:34",
        "price": 952.38,
        "volume": 1375
      },
      {
        "time": "2025-05-20 03:30:44",
        "price": 896.0,
        "volume": 1450
      },
      {
        "time": "2025-05-20 03:30:54",
        "price": 868.42,
        "volume": 1448
      },
      {
        "time": "2025-05-20 03:31:04",
        "price": 904.22,
        "volume": 1430
      },
      {
        "time": "2025-05-20 03:51:17",
        "price": 812.69,
        "volume": 1525
      },
      {
        "time": "2025-05-20 03:51:27",
        "price": 827.7,
        "volume": 1564
      },
      {
        "time": "2025-05-20 03:51:37",
        "price": 735.77,
        "volume": 1573
      },
      {
        "time": "2025-05-20 03:51:47",
        "price": 742.57,
        "volume": 1635
      },
      {
        "time": "2025-05-20 03:51:49",
        "price": 839.74,
        "volume": 1708
      },
      {
        "time": "2025-05-20 03:51:59",
        "price": 863.54,
        "volume": 1708
      },
      {
        "time": "2025-05-20 03:52:09",
        "price": 858.57,
        "volume": 1793
      },
      {
        "time": "2025-05-20 03:52:19",
        "price": 826.84,
        "volume": 1694
      },
      {
        "time": "2025-05-20 03:52:29",
        "price": 835.94,
        "volume": 1716
      },
      {
        "time": "2025-05-20 03:52:39",
        "price": 859.27,
        "volume": 1735
      },
      {
        "time": "2025-05-20 03:52:49",
        "price": 930.91,
        "volume": 1805
      },
      {
        "time": "2025-05-20 03:52:59",
        "price": 894.08,
        "volume": 1732
      }
    ]
  }
}